rabbitChat/__init__.py
rabbitChat/server.py
rabbitChat/settings.py
rabbitChat/urls.py
rabbitChat/utils.py
rabbitChat/apps/__init__.py
rabbitChat/apps/main/__init__.py
rabbitChat/apps/main/urls.py
rabbitChat/apps/main/views.py
rabbitChat/apps/rabbitmq/__init__.py
rabbitChat/apps/rabbitmq/pubsub.py
rabbitChat/static/css/style.css
rabbitChat/static/js/date.js
rabbitChat/static/js/script.js
rabbitChat/templates/index.html
rabbitChat-1.0.0.dist-info/DESCRIPTION.rst
rabbitChat-1.0.0.dist-info/METADATA
rabbitChat-1.0.0.dist-info/RECORD
rabbitChat-1.0.0.dist-info/WHEEL
rabbitChat-1.0.0.dist-info/entry_points.txt
rabbitChat-1.0.0.dist-info/metadata.json
rabbitChat-1.0.0.dist-info/top_level.txt
