Metadata-Version: 2.0
Name: rabbitChat
Version: 1.0.0
Summary: A Chat Server based on AMQP using RabbitMQ message broker implementing AMQP, websocket, sockjs, sockjs-tornado, tornado, and amqp python client library, Pika
Home-page: https://github.com/anirbanroydas/rabbitChat
Author: Anirban Roy Das
Author-email: anirban.nick@gmail.com
License: MIT
Keywords: chat server amqp protocol rabbitmq message broker via sockjs websocket tornado with sockjs-tornado and amqp python client library Pika
Platform: UNKNOWN
Classifier: Development Status :: 4 - Beta
Classifier: Intended Audience :: Developers
Classifier: License :: OSI Approved :: MIT License
Classifier: Natural Language :: English
Classifier: Operating System :: OS Independent
Classifier: Programming Language :: Python
Classifier: Programming Language :: Python :: 2
Classifier: Programming Language :: Python :: 2.7
Classifier: Programming Language :: Python :: Implementation :: CPython
Requires-Dist: pika
Requires-Dist: setuptools (>=0.7.0)
Requires-Dist: sockjs-tornado
Requires-Dist: tornado (>=2.2.1)
